Metadata-Version: 2.0
Name: rtsprofile-aist
Version: 4.1.5
Summary: Library to read, manipulate and write RT system profiles using the RTSProfile XML schema.
Home-page: https://github.com/OpenRTM/rtsprofile
Author: Geoffrey Biggs, Noriaki Ando
Author-email: n-ando@aist.go.jp
License: LGPL3
Platform: UNKNOWN
Classifier: Development Status :: 5 - Production/Stable
Classifier: Intended Audience :: Developers
Classifier: License :: OSI Approved :: GNU Lesser General Public License v3 (LGPLv3)
Classifier: Natural Language :: English
Classifier: Operating System :: OS Independent
Classifier: Programming Language :: Python :: 2.7
Classifier: Programming Language :: Python :: 3.5
Classifier: Programming Language :: Python :: 3.6
Classifier: Programming Language :: Python :: 3.7
Classifier: Programming Language :: Python :: 3.8
Classifier: Programming Language :: Python :: 3.9
Classifier: Topic :: Software Development
